btrader
