Metadata-Version: 2.1
Name: btrader
Version: 0.1.5
Summary: Arbitrage trading bot for Binance, based on https://github.com/bmino/binance-triangle-arbitrage
Home-page: https://github.com/gabriel-milan/btrader
Author: Gabriel Gazola Milan
Author-email: gabriel.gazola@poli.ufrj.br
License: GPL-3.0
Keywords: bot,algotrading,cryptocurrencies,binance,bitcoin,arbitrage
Platform: UNKNOWN
Classifier: Development Status :: 4 - Beta
Classifier: Intended Audience :: Developers
Classifier: Topic :: Software Development :: Libraries :: Python Modules
Classifier: License :: OSI Approved :: GNU General Public License v3 (GPLv3)
Classifier: Programming Language :: Python :: 3
Classifier: Programming Language :: Python :: 3.4
Classifier: Programming Language :: Python :: 3.5
Classifier: Programming Language :: Python :: 3.6
Classifier: Programming Language :: Python :: 3.7
Classifier: Programming Language :: Python :: 3.8
